dhesend/__init__.py
dhesend/_email.py
dhesend/api_paths.py
dhesend/apikey.py
dhesend/constants.py
dhesend/dhesend_main.py
dhesend/domain.py
dhesend/project_type.py
dhesend/webhook.py
dhesend-1.0.3.dist-info/LICENCE
dhesend-1.0.3.dist-info/METADATA
dhesend-1.0.3.dist-info/WHEEL
dhesend-1.0.3.dist-info/top_level.txt
dhesend-1.0.3.dist-info/RECORD
