Metadata-Version: 2.2
Name: dhesend
Version: 1.0.3
Summary: Dhesend Official Python SDK.
Home-page: https://github.com/dhesend/dhesend-python
Author: Dhesend
Author-email: 
License: MIT
Classifier: Development Status :: 5 - Production/Stable
Classifier: License :: OSI Approved :: MIT License
Classifier: Intended Audience :: Developers
Classifier: Programming Language :: Python :: 3
Classifier: Operating System :: OS Independent
License-File: LICENCE
Requires-Dist: requests>=2.32.3
Dynamic: author
Dynamic: classifier
Dynamic: description
Dynamic: description-content-type
Dynamic: home-page
Dynamic: license
Dynamic: requires-dist
Dynamic: summary
